asyncinit/__init__.py
asyncinit-0.2.3.dist-info/METADATA
asyncinit-0.2.3.dist-info/RECORD
asyncinit-0.2.3.dist-info/WHEEL
asyncinit-0.2.3.dist-info/top_level.txt
