Metadata-Version: 2.1
Name: asyncinit
Version: 0.2.3
Summary: Class decorator to enable async __init__
Home-page: https://github.com/kchmck/pyasyncinit
Author: Mick Koch
Author-email: mick@kochm.co
License: MIT
Keywords: async init asyncio
Platform: UNKNOWN
Classifier: Development Status :: 4 - Beta
Classifier: Intended Audience :: Developers
Classifier: Operating System :: OS Independent
Classifier: Programming Language :: Python :: 3 :: Only
Classifier: Programming Language :: Python :: 3.5
Classifier: Programming Language :: Python :: 3.6
Classifier: License :: OSI Approved :: MIT License
